mdscuda/__init__.py
mdscuda/example.py
mdscuda/example_digits.py
mdscuda/example_iris.py
mdscuda/example_khan.py
mdscuda/example_random.py
mdscuda/mds.py
mdscuda/minkowski.py
mdscuda/utils.py
mdscuda-0.1.3.dist-info/LICENSE
mdscuda-0.1.3.dist-info/METADATA
mdscuda-0.1.3.dist-info/WHEEL
mdscuda-0.1.3.dist-info/top_level.txt
mdscuda-0.1.3.dist-info/RECORD
