Metadata-Version: 2.1
Name: mdscuda
Version: 0.1.3
Summary: CUDA implementation of Multidimensional Scaling
Home-page: https://github.com/SethEBaldwin/mdscuda
Author: Seth Baldwin
Author-email: seth.e.baldwin@gmail.com
License: UNKNOWN
Project-URL: Bug Tracker, https://github.com/SethEBaldwin/mdscuda/issues
Platform: UNKNOWN
Classifier: Programming Language :: Python :: 3
Classifier: License :: OSI Approved :: MIT License
Classifier: Operating System :: OS Independent
Requires-Python: >=3.7
Requires-Dist: numpy (>=1.19.0)
Requires-Dist: scipy (>=1.6.0)
Requires-Dist: numba (>=0.51.0)
